tno/mpc/mpyc/floating_point/__init__.py
tno/mpc/mpyc/floating_point/_add.py
tno/mpc/mpyc/floating_point/_mpyc_cached_attribute.py
tno/mpc/mpyc/floating_point/_mul.py
tno/mpc/mpyc/floating_point/_plaintext_helper_functions.py
tno/mpc/mpyc/floating_point/_rt.py
tno/mpc/mpyc/floating_point/_sys.py
tno/mpc/mpyc/floating_point/basic_functions.py
tno/mpc/mpyc/floating_point/extended_coroutine.py
tno/mpc/mpyc/floating_point/py.typed
tno/mpc/mpyc/floating_point/secure_bit_length.py
tno/mpc/mpyc/floating_point/secure_floating_point.py
tno/mpc/mpyc/floating_point/test/__init__.py
tno/mpc/mpyc/floating_point/test/conftest.py
tno/mpc/mpyc/floating_point/test/multiplayer_script.py
tno/mpc/mpyc/floating_point/test/test_basic_functionality.py
tno/mpc/mpyc/floating_point/test/test_mpyc_cached_attribute.py
tno/mpc/mpyc/floating_point/test/test_plaintext_helper_functions.py
tno/mpc/mpyc/floating_point/test/test_secure_floating_point_with_mpyc_fixture.py
tno/mpc/mpyc/floating_point/test/test_secure_floating_point_without_mpyc_fixture.py
tno/mpc/mpyc/floating_point/test/util.py
tno/mpc/mpyc/floating_point/vendor/__init__.py
tno/mpc/mpyc/floating_point/vendor/mpyc/__init__.py
tno/mpc/mpyc/floating_point/vendor/mpyc/_divmod.py
tno/mpc/mpyc/floating_point/vendor/mpyc/_trunc.py
tno.mpc.mpyc.floating_point-0.13.0.dist-info/LICENSE
tno.mpc.mpyc.floating_point-0.13.0.dist-info/METADATA
tno.mpc.mpyc.floating_point-0.13.0.dist-info/WHEEL
tno.mpc.mpyc.floating_point-0.13.0.dist-info/top_level.txt
tno.mpc.mpyc.floating_point-0.13.0.dist-info/RECORD
