Metadata-Version: 2.1
Name: tno.mpc.mpyc.floating_point
Version: 0.13.0
Summary: Implementation of secure floating point numbers for MPyC
Author-email: TNO PET Lab <petlab@tno.nl>
Maintainer-email: TNO PET Lab <petlab@tno.nl>
License: Apache License, Version 2.0
Project-URL: Homepage, https://pet.tno.nl/
Project-URL: Documentation, https://docs.pet.tno.nl/mpc/mpyc/floating_point/0.13.0
Project-URL: Source, https://github.com/TNO-MPC/mpyc.floating_point
Keywords: TNO,MPC,multi-party computation,MPyC,secure floating point
Platform: any
Classifier: License :: OSI Approved :: Apache Software License
Classifier: Programming Language :: Python :: 3
Classifier: Operating System :: OS Independent
Classifier: Intended Audience :: Developers
Classifier: Intended Audience :: Information Technology
Classifier: Intended Audience :: Science/Research
Classifier: Typing :: Typed
Classifier: Topic :: Security :: Cryptography
Requires-Python: >=3.9
License-File: LICENSE
Requires-Dist: mpyc~=0.10.0
Requires-Dist: tno.mpc.mpyc.stubs>=2.5.0
Requires-Dist: typing_extensions; python_version < "3.10"
Provides-Extra: gmpy
Requires-Dist: gmpy2>=2.1.0; extra == "gmpy"
Provides-Extra: tests
Requires-Dist: pytest>=8.1; extra == "tests"
Requires-Dist: pytest-asyncio; extra == "tests"
